{
  "id": "3910bb8075e908306d1233e573a9af54592adc5f",
  "canonicalId": "e967cf42b630bf5496fcc4a9a531d348028182b1",
  "slug": "网易-mumu-pro-安卓模拟器被指控每-30-分钟静默执行-17-条系统侦察命令",
  "date": "2026-02-23",
  "publishedAt": "2026-02-23T00:00:00Z",
  "lang": "zh",
  "title": "网易 MuMu Pro 安卓模拟器被指控每 30 分钟静默执行 17 条系统侦察命令。",
  "summary": "网易旗下的 MuMu Player Pro（一款 macOS 平台的安卓模拟器）被指控通过 SensorsData 分析工具，每 30 分钟静默执行一次涉及 17 项内容的系统侦察命令，收集硬件序列号、UUID 和网络信息等数据。其隐私政策声明收集设备标识符和进程信息是为了网络安全与防作弊，但此次指控的具体采集范围、频率和深度并未在政策中完全披露。 此事之所以重要，是因为它对于网易这家大型科技公司旗下的一款广泛使用的模拟器的用户，提出了严重的隐私和透明度关切。如果指控属实，这种系统性的、未完全披露的详细系统和网络数据收集，可能构成了超出功能必要性的过度监控，使用户在不知情的情况下面临用户画像分析或安全风险。 被指控执行的命令包括扫描本地局域网设备、抓取带有完整命令行参数的运行进程、读取 hosts 文件以及查询内核参数等。虽然隐私政策以安全和防作弊为由解释数据收集，但调查显示其实际行为可能比明确声明的范围更广、频率更高。",
  "score": 7,
  "tags": [
    "privacy",
    "security",
    "android-emulators",
    "data-collection",
    "telemetry"
  ],
  "sources": [
    {
      "platform": "telegram",
      "author": "Feb 22, 11:31"
    }
  ],
  "originalUrl": "https://gist.github.com/interpiduser5/547d8a7baec436f24b7cce89dd4ae1ea",
  "originalSite": "gist.github.com",
  "context": "MuMu Pro 这类安卓模拟器允许用户在 macOS 或 Windows 等非安卓操作系统上运行安卓应用程序。遥测技术，即从软件或硬件自动收集并传输数据，常用于分析和调试，但应透明披露。SensorsData 是一个用于收集用户和系统数据的知名分析 SDK。像 UUID 这样的硬件标识符可用于跨应用程序的持久性设备跟踪。",
  "discussion": "",
  "references": [],
  "image": null,
  "fullText": null
}