{
  "id": "601cc9c9df8d22512d883f4d55c0940dabb12a23",
  "canonicalId": "65886da9362017d600a101e8503ca6c01e54fdb2",
  "slug": "荷兰暂停依据商品可得性法对中国芯片制造商安世半导体的管制令",
  "date": "2026-03-07",
  "publishedAt": "2026-03-07T00:00:00Z",
  "lang": "zh",
  "title": "荷兰暂停依据《商品可得性法》对中国芯片制造商安世半导体的管制令",
  "summary": "荷兰政府于 11 月 19 日宣布，暂停依据《商品可得性法》对中资芯片制造商安世半导体 (Nexperia) 实施的干预令，将控制权归还给其中国母公司闻泰科技 (Wingtech)。荷兰经济事务大臣卡雷曼斯表示，此举是“善意的表示”。 这一决定标志着对半导体供应链一次重大地缘政治干预的重大逆转，可能缓解荷兰与中国在技术安全方面的紧张关系。这可能预示着欧洲国家在关键的芯片产业中，如何在国家安全关切与对华经济联系之间寻求平衡的策略转变。 荷兰政府最初于 2025 年 10 月援引了很少使用的《商品可得性法》，以接管安世半导体的控制权，理由是担心技术可能转移至其中方母公司闻泰科技。此次暂停将运营控制权交还闻泰科技，但未来进行干预的法律框架依然存在。",
  "score": 7,
  "tags": [
    "semiconductors",
    "geopolitics",
    "trade-policy",
    "supply-chain",
    "china-tech"
  ],
  "sources": [
    {
      "platform": "telegram",
      "author": "Mar 6, 08:08"
    }
  ],
  "originalUrl": "https://t.me/zaihuapd/40069",
  "originalSite": "t.me",
  "context": "安世半导体是一家总部位于荷兰奈梅亨的主要半导体制造商，在全球拥有超过 15,000 名员工。近年来，它被中国公司闻泰科技收购。荷兰的《商品可得性法》是一项允许政府干预企业以确保关键商品供应的法律，其在 2025 年 10 月被用于针对安世半导体是前所未有的，这与西方对中国获取先进半导体技术的更广泛担忧有关。",
  "discussion": "",
  "references": [
    {
      "title": "Nexperia - Wikipedia",
      "url": "https://en.wikipedia.org/wiki/Nexperia"
    },
    {
      "title": "Nexperia: Dutch government takes control of Chinese -owned...",
      "url": "https://www.cnn.com/2025/10/13/tech/dutch-government-china-nexperia-chipmaker-intl"
    }
  ],
  "image": null,
  "fullText": null
}