{
  "id": "981f5337f7046ded8bbd828c91900ca76c8f24c7",
  "canonicalId": "9567eeab7724822f626e9fcaf204c4e496bef565",
  "slug": "香港金管局向碇点金融及汇丰银行发出首批稳定币发行人牌照",
  "date": "2026-04-11",
  "publishedAt": "2026-04-11T00:00:00Z",
  "lang": "zh",
  "title": "香港金管局向碇点金融及汇丰银行发出首批稳定币发行人牌照",
  "summary": "4 月 10 日，香港金融管理局根据《稳定币条例》向碇点金融科技有限公司及香港上海汇丰银行有限公司授予首批稳定币发行人牌照，允许其在香港发行稳定币。牌照于当日生效，两家持牌机构计划在完成相关准备工作后于未来数月内开展业务。 这是香港金融科技领域的重要监管里程碑，为稳定币发行建立了明确的法律框架，可能吸引更多机构参与者并推动加密货币采用。作为全球主要金融中心，香港的监管方式可能影响其他正在制定稳定币法规的司法管辖区。 牌照是根据香港《稳定币条例》颁发的，该条例为稳定币发行人制定了具体要求。碇点金融科技（一家金融科技公司）和汇丰银行（一家传统银行机构）均获得牌照，表明监管框架同时容纳了新进入者和成熟的金融机构。",
  "score": 7,
  "tags": [
    "stablecoin",
    "regulatory",
    "fintech",
    "Hong Kong",
    "banking"
  ],
  "sources": [
    {
      "platform": "telegram",
      "author": "Apr 10, 09:15"
    }
  ],
  "originalUrl": "https://www.cls.cn/detail/2340578",
  "originalSite": "cls.cn",
  "context": "稳定币是一种旨在通过锚定法定货币或商品等储备资产来保持价值稳定的加密货币。针对稳定币发行人的监管框架（如美国的 GENIUS 法案）通常建立许可要求和审慎标准，以确保消费者保护和金融稳定。香港的《稳定币条例》代表了亚洲金融市场类似的监管方式。",
  "discussion": "",
  "references": [
    {
      "title": "The GENIUS Act: A Framework for U.S. Stablecoin Issuance ...",
      "url": "https://www.sidley.com/en/insights/newsupdates/2025/07/the-genius-act-a-framework-for-us-stablecoin-issuance"
    },
    {
      "title": "GENIUS Act AML Compliance Guide for Payment Stablecoin ...",
      "url": "https://complyfactor.com/genius-act-ppsi-aml-compliance-stablecoin-issuers/"
    }
  ],
  "image": null,
  "fullText": null
}