{
  "id": "ab2ee029b3324cfd28c46dab5c643114c0f8eb7a",
  "canonicalId": "1bb6fff22bd1ac984453b71a41c579885b52a23c",
  "slug": "perplexity-发布-personal-computer-软件将-mac-转化为-ai-助手",
  "date": "2026-04-18",
  "publishedAt": "2026-04-18T00:00:00Z",
  "lang": "zh",
  "title": "Perplexity 发布 Personal Computer 软件，将 Mac 转化为 AI 助手",
  "summary": "Perplexity 发布了 Personal Computer 软件，面向 Perplexity Max 订阅者和候补名单用户开放，该软件将 Mac 转化为 AI 助手，能够自主管理 Gmail、Slack 和 Salesforce 等应用中的任务。该系统以目标为导向，将复杂目标分解为子任务，并协调 AI 工具完成工作。 这一发布代表了 AI 生产力工具的重大进步，通过实现跨多个平台的自主任务自动化，可能提升个人和企业用户的效率。它符合将 AI 深度集成到日常工作流程的趋势，提供了更无缝和智能的助手体验。 该软件深度集成于 Mac 应用，可访问本地文件和原生程序，并包含企业功能，如 SOC 2 合规性、审计日志和沙盒执行以增强安全性。然而，由于数据处理依赖云端服务器而非纯本地运行，尽管有用户审批和“一键关闭”等安全机制，隐私安全仍是关注焦点。",
  "score": 7,
  "tags": [
    "AI",
    "Productivity",
    "Software Release",
    "Mac",
    "Automation"
  ],
  "sources": [
    {
      "platform": "telegram",
      "author": "Apr 17, 03:34"
    }
  ],
  "originalUrl": "https://www.cultofmac.com/news/perplexity-personal-computer",
  "originalSite": "cultofmac.com",
  "context": "Perplexity 是一家 AI 搜索引擎公司，Perplexity Max 是其最高级的订阅层级，提供对最新 AI 模型和文件创建等功能的访问。SOC 2 合规性是软件中数据安全的标准，确保对敏感信息的控制，而沙盒执行则隔离代码以防止 AI 应用中的系统风险。",
  "discussion": "",
  "references": [
    {
      "title": "Perplexity Max | Perplexity Help Center",
      "url": "https://www.perplexity.ai/help-center/en/articles/11680686-perplexity-max"
    },
    {
      "title": "The Best SOC 2 Compliance Software & Tools",
      "url": "https://www.planetcompliance.com/soc-2/best-soc-2-compliance-software/"
    },
    {
      "title": "Sandboxing AI agents, 100x faster",
      "url": "https://blog.cloudflare.com/dynamic-workers/"
    }
  ],
  "image": null,
  "fullText": null
}