{
  "id": "dfd7c991e9690a5861f8b112bc04ea844d34ea1a",
  "canonicalId": "d349374bd9076dd209bafdaf9fe5bc18e2a384d9",
  "slug": "小米开源-omnivoice646-语种语音克隆-tts",
  "date": "2026-05-08",
  "publishedAt": "2026-05-08T00:00:00Z",
  "lang": "zh",
  "title": "小米开源 OmniVoice：646 语种语音克隆 TTS",
  "summary": "小米开源了 OmniVoice，这是一个支持 600 多种语言的极简双向 Transformer 架构的多语言零样本 TTS 模型，训练速度达到每天 10 万小时，PyTorch 推理速度达到 40 倍实时。 此次开源将高质量多语言语音克隆技术普及化，在 24 种语言的测试中超越商业系统，在 102 种语言中逼近真实语音，为全球开发者提供了跨语言定制、带噪适配等能力。 OmniVoice 基于 50 个开源数据集构建了 58 万小时、646 种语言的训练集，采用全码本随机掩蔽和大语言模型预训练参数来提升效率和可懂度。",
  "score": 8,
  "tags": [
    "TTS",
    "voice cloning",
    "open-source",
    "multilingual",
    "Xiaomi"
  ],
  "sources": [
    {
      "platform": "telegram",
      "author": "May 7, 10:06"
    }
  ],
  "originalUrl": "https://mp.weixin.qq.com/s/TCS_Sd10g_rvf1cszw673A",
  "originalSite": "mp.weixin.qq.com",
  "context": "文本转语音（TTS）是将书面文字转换为语音音频，语音克隆则是复制目标说话人的声音特征。OmniVoice 使用双向 Transformer 架构（类似 BERT）和码本表示离散音频，并利用预训练大语言模型参数来加速训练。全码本随机掩蔽是一种训练技术，在训练时随机掩蔽所有码本条目，以提升鲁棒性。",
  "discussion": "",
  "references": [
    {
      "title": "GitHub - k2-fsa/OmniVoice: High-Quality Voice Cloning TTS for 600+ Languages · GitHub",
      "url": "https://github.com/k2-fsa/OmniVoice"
    },
    {
      "title": "k2-fsa/OmniVoice · Hugging Face",
      "url": "https://huggingface.co/k2-fsa/OmniVoice"
    }
  ],
  "image": null,
  "fullText": null
}