{
  "id": "e353f915372cc7afee15098df4353b4c060c9ad1",
  "canonicalId": "03b6daee7ee45e896860c8cc1b8892b8c73acf7b",
  "slug": "苹果发布采用全新-fusion-architecture-的-m5-pro-和-m5-max-芯片用于-macbook-pro",
  "date": "2026-03-07",
  "publishedAt": "2026-03-07T00:00:00Z",
  "lang": "zh",
  "title": "苹果发布采用全新 Fusion Architecture 的 M5 Pro 和 M5 Max 芯片，用于 MacBook Pro",
  "summary": "苹果宣布推出 M5 Pro 和 M5 Max 芯片，采用全新的 Fusion Architecture 设计，将两个芯片组合成单一 SoC。这些芯片为新款 MacBook Pro 提供动力，配备 18 核 CPU，包括超级核心和性能核心，据称可为专业工作负载带来显著的性能提升。 这标志着 Apple Silicon 的一次重大代际飞跃，可能重新定义专业笔记本电脑在创意和技术领域的性能基准。这种架构转变可能显著影响视频编辑、3D 渲染和软件开发等工作流程，巩固苹果在高端计算市场的地位。 M5 Pro 和 M5 Max 采用 18 核 CPU 配置，包括 6 个超级核心和 12 个性能核心。全新的 Fusion Architecture 是一个关键的设计变更，从单片式 SoC 转变为将两个芯片组合成一个集成封装的设计。",
  "score": 9,
  "tags": [
    "apple-silicon",
    "hardware",
    "macbook",
    "computer-architecture",
    "professional-computing"
  ],
  "sources": [
    {
      "platform": "telegram",
      "author": "Mar 6, 00:10"
    }
  ],
  "originalUrl": "https://t.me/zaihuapd/40055",
  "originalSite": "t.me",
  "context": "Apple Silicon 指的是苹果自研的系统级芯片（SoC）设计，它将 CPU、GPU 和其他组件集成到一块硅片上。SoC 是一种集成电路，它将计算机的全部或大部分组件组合到单个芯片上，从而提高性能和能效。苹果此前在 A10 Fusion 等处理器设计中就使用过 \"Fusion\" 这一术语，该设计结合了高性能和高能效核心。",
  "discussion": "",
  "references": [
    {
      "title": "System on a chip - Wikipedia",
      "url": "https://en.wikipedia.org/wiki/System_on_a_chip"
    },
    {
      "title": "Apple A10 Fusion Are Bigger Than the Competition – Apple",
      "url": "https://wccftech.com/apple-a10-fusion-cores-bigger-than-competition/"
    }
  ],
  "image": null,
  "fullText": null
}