{
  "id": "e6520b84142d3806976ce5169f5359157d277cbe",
  "canonicalId": "2d8d3f9cd0c5cf779cc2921bd4694e3b3802d08d",
  "slug": "ai-是否在重蹈前端失落的十年",
  "date": "2026-05-30",
  "publishedAt": "2026-05-29T11:09:00Z",
  "lang": "zh",
  "title": "AI 是否在重蹈前端“失落的十年”？",
  "summary": "一篇博文指出，AI 工具正在导致前端专业知识和代码质量下降，让人联想到当年 jQuery 和 React 等框架抽象掉基本 Web 技能的“失落的十年”。 这场争论之所以重要，是因为它揭示了 AI 驱动的效率提升与前端工匠精神丧失之间的紧张关系，可能影响网页可访问性、性能和整体软件质量。 文章提到过去开发者因框架抽象而丧失底层技能的时期，而现在的 AI 代码生成可能加速这一趋势。社区评论反驳称，早期的转变大多是良性的，AI 同样减少了偶然复杂性。",
  "score": 8,
  "tags": [
    "AI",
    "frontend development",
    "software engineering",
    "quality",
    "community debate"
  ],
  "sources": [
    {
      "platform": "hackernews",
      "author": "xyzal",
      "discussionUrl": "https://news.ycombinator.com/item?id=48321631"
    }
  ],
  "originalUrl": "https://mastrojs.github.io/blog/2026-05-23-is-AI-causing-a-repeat-of-frontends-lost-decade/",
  "originalSite": "mastrojs.github.io",
  "context": "前端开发的“失落的十年”指的是 2000 年代末，jQuery 以及后来的 React、Vue 和 Angular 将直接 DOM 操作抽象化，导致一代开发者对原生 HTML、CSS 和 JavaScript 不够熟悉。如今，AI 代码助手能够生成完整组件，进一步拉大了开发者与基础知识的距离，这一模式正在重演。",
  "discussion": "评论情绪不一：有人认同 AI 正在降低质量，也有人认为过去所谓的“专业知识”往往是在处理不必要的复杂性。多位评论者指出，过去的行业并非充满熟练工匠，只要更多人能构建东西，这种权衡是可以接受的。",
  "references": [
    {
      "title": "Is AI causing a repeat of Frontend ’s Lost Decade ? | Mastro Blog",
      "url": "https://mastrojs.github.io/blog/2026-05-23-is-AI-causing-a-repeat-of-frontends-lost-decade/"
    },
    {
      "title": "Front-end web development - Wikipedia",
      "url": "https://en.m.wikipedia.org/wiki/Front-end_web_development"
    },
    {
      "title": "Is AI causing a repeat of Front end 's Lost Decade ? - AI Espionage",
      "url": "https://aiespionage.net/tech-deep-dives/is-ai-causing-a-repeat-of-front-end-s-lost-decade/"
    }
  ],
  "image": null,
  "fullText": null
}